evion_ndvi_sdk/__init__.py
evion_ndvi_sdk/cli.py
evion_ndvi_sdk/client.py
evion_ndvi_sdk/exceptions.py
evion_ndvi_sdk-1.0.0.dist-info/LICENSE
evion_ndvi_sdk-1.0.0.dist-info/METADATA
evion_ndvi_sdk-1.0.0.dist-info/WHEEL
evion_ndvi_sdk-1.0.0.dist-info/entry_points.txt
evion_ndvi_sdk-1.0.0.dist-info/top_level.txt
evion_ndvi_sdk-1.0.0.dist-info/RECORD
