Metadata-Version: 2.1
Name: evion-ndvi-sdk
Version: 1.0.0
Summary: Python SDK for EvionAI NDVI prediction service
Home-page: https://github.com/evionai/evion-ndvi-sdk
Author: EvionAI
Author-email: support@evionai.com
Classifier: Development Status :: 4 - Beta
Classifier: Intended Audience :: Developers
Classifier: Programming Language :: Python :: 3
Classifier: Programming Language :: Python :: 3.7
Classifier: Operating System :: OS Independent
Requires-Python: >=3.7
License-File: LICENSE
Requires-Dist: requests >=2.25.0
Requires-Dist: Pillow >=8.0.0
Requires-Dist: numpy >=1.19.0
Requires-Dist: matplotlib >=3.3.0
